nutstosoup/__init__.py
nutstosoup/__main__.py
nutstosoup-0.2.0.dist-info/METADATA
nutstosoup-0.2.0.dist-info/WHEEL
nutstosoup-0.2.0.dist-info/RECORD
